grassp/__init__.py
grassp/_version.py
grassp/conftest.py
grassp/util.py
grassp/datasets/__init__.py
grassp/datasets/create_subcellular_annotations.ipynb
grassp/datasets/example_data.py
grassp/datasets/metadata.py
grassp/datasets/external/custom_goterms_genes_reviewed.gmt
grassp/datasets/external/subcellular_annotations.tsv
grassp/io/__init__.py
grassp/io/read.py
grassp/plotting/__init__.py
grassp/plotting/clustering.py
grassp/plotting/heatmaps.py
grassp/plotting/integration.py
grassp/plotting/qc.py
grassp/plotting/ternary.py
grassp/preprocessing/__init__.py
grassp/preprocessing/enrichment.py
grassp/preprocessing/imputation.py
grassp/preprocessing/simple.py
grassp/preprocessing/utils.py
grassp/tests/__init__.py
grassp/tests/test_placeholder.py
grassp/tools/__init__.py
grassp/tools/clustering.py
grassp/tools/enrichment.py
grassp/tools/integration.py
grassp/tools/scoring.py
grassp-0.0.2.post9.dist-info/METADATA
grassp-0.0.2.post9.dist-info/WHEEL
grassp-0.0.2.post9.dist-info/entry_points.txt
grassp-0.0.2.post9.dist-info/top_level.txt
grassp-0.0.2.post9.dist-info/RECORD
