Metadata-Version: 2.4
Name: grassp
Version: 0.0.2.post9
Summary: A python package to facilitate Organellar profiling
License: BSD 3-Clause License
Project-URL: homepage, https://github.com/czbiohub/some-package
Project-URL: documentation, https://github.com/czbiohub/some-package
Project-URL: repository, https://github.com/czbiohub/some-package
Classifier: Development Status :: 3 - Alpha
Classifier: Intended Audience :: Science/Research
Classifier: Programming Language :: Python :: 3 :: Only
Classifier: Programming Language :: Python :: 3.10
Classifier: Programming Language :: Python :: 3.11
Classifier: Programming Language :: Python :: 3.12
Requires-Python: <4.0,>=3.7
Requires-Dist: anndata
Requires-Dist: markov_clustering
Requires-Dist: matplotlib
Requires-Dist: networkx
Requires-Dist: numpy
Requires-Dist: pandas
Requires-Dist: protdata
Requires-Dist: pysankeybeta
Requires-Dist: requests
Requires-Dist: scanpy[leiden]
Requires-Dist: scikit-learn
Requires-Dist: scipy
Requires-Dist: seaborn
Requires-Dist: umap-learn
Provides-Extra: dev
Requires-Dist: black~=25.1; extra == "dev"
Requires-Dist: flake8~=7.0; extra == "dev"
Requires-Dist: isort~=5.0; extra == "dev"
Requires-Dist: pre-commit~=3.0; extra == "dev"
Requires-Dist: pylint~=3.0; extra == "dev"
Requires-Dist: pytest~=8.0; extra == "dev"
Provides-Extra: notebook
Requires-Dist: jupyterlab; extra == "notebook"
Requires-Dist: matplotlib; extra == "notebook"
Provides-Extra: build
Requires-Dist: twine; extra == "build"
Requires-Dist: build; extra == "build"
Provides-Extra: docs
Requires-Dist: sphinx; extra == "docs"
Requires-Dist: sphinx-autodoc-typehints; extra == "docs"
Requires-Dist: scanpydoc[theme,typehints]>=0.15.1; extra == "docs"
Requires-Dist: myst_parser; extra == "docs"
